micropython_ds1841/__init__.py
micropython_ds1841/ds1841.py
micropython_ds1841/i2c_helpers.py
micropython_ds1841-0.1.2.dist-info/LICENSE
micropython_ds1841-0.1.2.dist-info/METADATA
micropython_ds1841-0.1.2.dist-info/WHEEL
micropython_ds1841-0.1.2.dist-info/top_level.txt
micropython_ds1841-0.1.2.dist-info/RECORD
