Metadata-Version: 2.1
Name: micropython-ds1841
Version: 0.1.2
Summary: MicroPython Driver for the DS1841 Potentiometer
Author-email: JDM <xxyx@mailmeto.mozmail.com>
License: MIT
Project-URL: Homepage, https://github.com/jposada202020/MicroPython_DS1841
Keywords: sensor,micropython,ds1841,driver,ds1841,potentiometer,analog,devices,resistance
Classifier: Intended Audience :: Developers
Classifier: Topic :: Software Development :: Libraries
Classifier: Topic :: Software Development :: Embedded Systems
Classifier: Topic :: System :: Hardware
Classifier: License :: OSI Approved :: MIT License
Classifier: Programming Language :: Python :: Implementation :: MicroPython
License-File: LICENSE
